tikdan/Tikdan.py
tikdan/__init__.py
tikdan-1.dist-info/LICENSE
tikdan-1.dist-info/METADATA
tikdan-1.dist-info/WHEEL
tikdan-1.dist-info/top_level.txt
tikdan-1.dist-info/RECORD
