Metadata-Version: 2.1
Name: tikdan
Version: 1
Summary: Unofficial api tiktok
Home-page: https://github.com/ALIILAPRO/Tikdan
Author: ALIILAPRO
Author-email: aliilapro@pm.me
License: UNKNOWN
Platform: UNKNOWN
Classifier: Development Status :: 3 - Alpha
Classifier: Intended Audience :: Developers
Classifier: License :: OSI Approved :: GNU General Public License v3 (GPLv3)
Classifier: Programming Language :: Python :: 3.7
Classifier: Programming Language :: Python :: 3.8
Classifier: Programming Language :: Python :: 3.9
Classifier: Programming Language :: Python :: 3.10
Requires-Dist: requests
